{
  "Xc4xYacTu-E": [
    {
      "speed": 1.0,
      "wer": 0.0,
      "cer": 0.0,
      "wer_absolute": 0.0,
      "cer_absolute": 0.0,
      "transcription_length": 22322,
      "is_baseline": true
    },
    {
      "speed": 1.1,
      "wer": 0.66,
      "cer": 0.41,
      "wer_absolute": 0.66,
      "cer_absolute": 0.41,
      "transcription_length": 22313,
      "is_baseline": false
    },
    {
      "speed": 1.2,
      "wer": 1.02,
      "cer": 0.72,
      "wer_absolute": 1.02,
      "cer_absolute": 0.72,
      "transcription_length": 22323,
      "is_baseline": false
    },
    {
      "speed": 1.5,
      "wer": 1.65,
      "cer": 1.39,
      "wer_absolute": 1.65,
      "cer_absolute": 1.39,
      "transcription_length": 22469,
      "is_baseline": false
    },
    {
      "speed": 2.0,
      "wer": 2.32,
      "cer": 1.47,
      "wer_absolute": 2.32,
      "cer_absolute": 1.47,
      "transcription_length": 22135,
      "is_baseline": false
    },
    {
      "speed": 2.5,
      "wer": 6.57,
      "cer": 4.83,
      "wer_absolute": 6.57,
      "cer_absolute": 4.83,
      "transcription_length": 21517,
      "is_baseline": false
    },
    {
      "speed": 1.3,
      "wer": 1.77,
      "cer": 1.36,
      "wer_absolute": 1.77,
      "cer_absolute": 1.36,
      "transcription_length": 22473,
      "is_baseline": false
    },
    {
      "speed": 1.4,
      "wer": 1.06,
      "cer": 0.69,
      "wer_absolute": 1.06,
      "cer_absolute": 0.69,
      "transcription_length": 22311,
      "is_baseline": false
    },
    {
      "speed": 1.6,
      "wer": 2.03,
      "cer": 1.15,
      "wer_absolute": 2.03,
      "cer_absolute": 1.15,
      "transcription_length": 22316,
      "is_baseline": false
    },
    {
      "speed": 1.7,
      "wer": 1.91,
      "cer": 1.36,
      "wer_absolute": 1.91,
      "cer_absolute": 1.36,
      "transcription_length": 22211,
      "is_baseline": false
    },
    {
      "speed": 1.8,
      "wer": 2.2,
      "cer": 1.78,
      "wer_absolute": 2.2,
      "cer_absolute": 1.78,
      "transcription_length": 22179,
      "is_baseline": false
    },
    {
      "speed": 1.9,
      "wer": 2.03,
      "cer": 1.39,
      "wer_absolute": 2.03,
      "cer_absolute": 1.39,
      "transcription_length": 22112,
      "is_baseline": false
    }
  ],
  "khan_academy_addition": [
    {
      "speed": 1.0,
      "wer": 0.0,
      "cer": 0.0,
      "wer_absolute": 0.0,
      "cer_absolute": 0.0,
      "transcription_length": 6092,
      "is_baseline": true
    },
    {
      "speed": 1.1,
      "wer": 1.47,
      "cer": 1.29,
      "wer_absolute": 1.47,
      "cer_absolute": 1.29,
      "transcription_length": 6072,
      "is_baseline": false
    },
    {
      "speed": 1.2,
      "wer": 1.33,
      "cer": 1.14,
      "wer_absolute": 1.33,
      "cer_absolute": 1.14,
      "transcription_length": 6143,
      "is_baseline": false
    },
    {
      "speed": 1.5,
      "wer": 2.72,
      "cer": 2.23,
      "wer_absolute": 2.72,
      "cer_absolute": 2.23,
      "transcription_length": 6112,
      "is_baseline": false
    },
    {
      "speed": 2.0,
      "wer": 15.61,
      "cer": 13.85,
      "wer_absolute": 15.61,
      "cer_absolute": 13.85,
      "transcription_length": 6455,
      "is_baseline": false
    },
    {
      "speed": 2.5,
      "wer": 20.54,
      "cer": 18.04,
      "wer_absolute": 20.54,
      "cer_absolute": 18.04,
      "transcription_length": 6185,
      "is_baseline": false
    },
    {
      "speed": 1.3,
      "wer": 2.36,
      "cer": 1.9,
      "wer_absolute": 2.36,
      "cer_absolute": 1.9,
      "transcription_length": 6092,
      "is_baseline": false
    },
    {
      "speed": 1.4,
      "wer": 1.69,
      "cer": 1.34,
      "wer_absolute": 1.69,
      "cer_absolute": 1.34,
      "transcription_length": 6177,
      "is_baseline": false
    },
    {
      "speed": 1.6,
      "wer": 14.36,
      "cer": 13.0,
      "wer_absolute": 14.36,
      "cer_absolute": 13.0,
      "transcription_length": 6421,
      "is_baseline": false
    },
    {
      "speed": 1.7,
      "wer": 8.62,
      "cer": 8.41,
      "wer_absolute": 8.62,
      "cer_absolute": 8.41,
      "transcription_length": 6251,
      "is_baseline": false
    },
    {
      "speed": 1.8,
      "wer": 14.87,
      "cer": 13.53,
      "wer_absolute": 14.87,
      "cer_absolute": 13.53,
      "transcription_length": 6418,
      "is_baseline": false
    },
    {
      "speed": 1.9,
      "wer": 3.61,
      "cer": 2.9,
      "wer_absolute": 3.61,
      "cer_absolute": 2.9,
      "transcription_length": 6153,
      "is_baseline": false
    }
  ],
  "riXcZT2ICjA": [
    {
      "speed": 1.0,
      "wer": 0.0,
      "cer": 0.0,
      "wer_absolute": 0.0,
      "cer_absolute": 0.0,
      "transcription_length": 9394,
      "is_baseline": true
    },
    {
      "speed": 1.1,
      "wer": 2.36,
      "cer": 2.1,
      "wer_absolute": 2.36,
      "cer_absolute": 2.1,
      "transcription_length": 9408,
      "is_baseline": false
    },
    {
      "speed": 1.2,
      "wer": 4.68,
      "cer": 3.82,
      "wer_absolute": 4.68,
      "cer_absolute": 3.82,
      "transcription_length": 9720,
      "is_baseline": false
    },
    {
      "speed": 1.5,
      "wer": 3.62,
      "cer": 3.02,
      "wer_absolute": 3.62,
      "cer_absolute": 3.02,
      "transcription_length": 9611,
      "is_baseline": false
    },
    {
      "speed": 2.0,
      "wer": 9.94,
      "cer": 8.45,
      "wer_absolute": 9.94,
      "cer_absolute": 8.45,
      "transcription_length": 9435,
      "is_baseline": false
    },
    {
      "speed": 2.5,
      "wer": 20.8,
      "cer": 17.68,
      "wer_absolute": 20.8,
      "cer_absolute": 17.68,
      "transcription_length": 10032,
      "is_baseline": false
    },
    {
      "speed": 1.3,
      "wer": 2.61,
      "cer": 2.2,
      "wer_absolute": 2.61,
      "cer_absolute": 2.2,
      "transcription_length": 9471,
      "is_baseline": false
    },
    {
      "speed": 1.4,
      "wer": 2.61,
      "cer": 2.16,
      "wer_absolute": 2.61,
      "cer_absolute": 2.16,
      "transcription_length": 9460,
      "is_baseline": false
    },
    {
      "speed": 1.6,
      "wer": 4.1,
      "cer": 3.4,
      "wer_absolute": 4.1,
      "cer_absolute": 3.4,
      "transcription_length": 9488,
      "is_baseline": false
    },
    {
      "speed": 1.7,
      "wer": 4.34,
      "cer": 3.47,
      "wer_absolute": 4.34,
      "cer_absolute": 3.47,
      "transcription_length": 9481,
      "is_baseline": false
    },
    {
      "speed": 1.8,
      "wer": 7.29,
      "cer": 5.91,
      "wer_absolute": 7.29,
      "cer_absolute": 5.91,
      "transcription_length": 9722,
      "is_baseline": false
    },
    {
      "speed": 1.9,
      "wer": 9.12,
      "cer": 7.32,
      "wer_absolute": 9.12,
      "cer_absolute": 7.32,
      "transcription_length": 9926,
      "is_baseline": false
    }
  ],
  "L45Q1_psDqk": [
    {
      "speed": 1.0,
      "wer": 0.0,
      "cer": 0.0,
      "wer_absolute": 0.0,
      "cer_absolute": 0.0,
      "transcription_length": 9003,
      "is_baseline": true
    },
    {
      "speed": 1.1,
      "wer": 3.53,
      "cer": 3.33,
      "wer_absolute": 3.53,
      "cer_absolute": 3.33,
      "transcription_length": 8704,
      "is_baseline": false
    },
    {
      "speed": 1.2,
      "wer": 3.53,
      "cer": 3.33,
      "wer_absolute": 3.53,
      "cer_absolute": 3.33,
      "transcription_length": 8700,
      "is_baseline": false
    },
    {
      "speed": 1.5,
      "wer": 0.18,
      "cer": 0.07,
      "wer_absolute": 0.18,
      "cer_absolute": 0.07,
      "transcription_length": 8998,
      "is_baseline": false
    },
    {
      "speed": 1.6,
      "wer": 0.3,
      "cer": 0.09,
      "wer_absolute": 0.3,
      "cer_absolute": 0.09,
      "transcription_length": 8990,
      "is_baseline": false
    },
    {
      "speed": 1.8,
      "wer": 0.61,
      "cer": 0.42,
      "wer_absolute": 0.61,
      "cer_absolute": 0.42,
      "transcription_length": 8965,
      "is_baseline": false
    },
    {
      "speed": 2.0,
      "wer": 0.49,
      "cer": 0.15,
      "wer_absolute": 0.49,
      "cer_absolute": 0.15,
      "transcription_length": 8996,
      "is_baseline": false
    },
    {
      "speed": 2.5,
      "wer": 1.58,
      "cer": 0.69,
      "wer_absolute": 1.58,
      "cer_absolute": 0.69,
      "transcription_length": 8975,
      "is_baseline": false
    },
    {
      "speed": 1.3,
      "wer": 0.24,
      "cer": 0.09,
      "wer_absolute": 0.24,
      "cer_absolute": 0.09,
      "transcription_length": 9010,
      "is_baseline": false
    },
    {
      "speed": 1.4,
      "wer": 0.3,
      "cer": 0.12,
      "wer_absolute": 0.3,
      "cer_absolute": 0.12,
      "transcription_length": 8994,
      "is_baseline": false
    },
    {
      "speed": 1.7,
      "wer": 0.24,
      "cer": 0.08,
      "wer_absolute": 0.24,
      "cer_absolute": 0.08,
      "transcription_length": 9005,
      "is_baseline": false
    },
    {
      "speed": 1.9,
      "wer": 0.43,
      "cer": 0.15,
      "wer_absolute": 0.43,
      "cer_absolute": 0.15,
      "transcription_length": 9008,
      "is_baseline": false
    }
  ],
  "x7X9w_GIm1s": [
    {
      "speed": 1.0,
      "wer": 0.0,
      "cer": 0.0,
      "wer_absolute": 0.0,
      "cer_absolute": 0.0,
      "transcription_length": 2747,
      "is_baseline": true
    },
    {
      "speed": 1.5,
      "wer": 0.85,
      "cer": 0.33,
      "wer_absolute": 0.85,
      "cer_absolute": 0.33,
      "transcription_length": 2749,
      "is_baseline": false
    },
    {
      "speed": 2.0,
      "wer": 4.45,
      "cer": 1.84,
      "wer_absolute": 4.45,
      "cer_absolute": 1.84,
      "transcription_length": 2748,
      "is_baseline": false
    },
    {
      "speed": 2.5,
      "wer": 6.36,
      "cer": 2.73,
      "wer_absolute": 6.36,
      "cer_absolute": 2.73,
      "transcription_length": 2729,
      "is_baseline": false
    },
    {
      "speed": 1.1,
      "wer": 0.42,
      "cer": 0.37,
      "wer_absolute": 0.42,
      "cer_absolute": 0.37,
      "transcription_length": 2754,
      "is_baseline": false
    },
    {
      "speed": 1.2,
      "wer": 1.48,
      "cer": 0.59,
      "wer_absolute": 1.48,
      "cer_absolute": 0.59,
      "transcription_length": 2762,
      "is_baseline": false
    },
    {
      "speed": 1.3,
      "wer": 1.48,
      "cer": 0.55,
      "wer_absolute": 1.48,
      "cer_absolute": 0.55,
      "transcription_length": 2760,
      "is_baseline": false
    },
    {
      "speed": 1.4,
      "wer": 1.06,
      "cer": 0.81,
      "wer_absolute": 1.06,
      "cer_absolute": 0.81,
      "transcription_length": 2756,
      "is_baseline": false
    },
    {
      "speed": 1.6,
      "wer": 2.12,
      "cer": 0.77,
      "wer_absolute": 2.12,
      "cer_absolute": 0.77,
      "transcription_length": 2754,
      "is_baseline": false
    },
    {
      "speed": 1.7,
      "wer": 2.75,
      "cer": 0.88,
      "wer_absolute": 2.75,
      "cer_absolute": 0.88,
      "transcription_length": 2763,
      "is_baseline": false
    },
    {
      "speed": 1.8,
      "wer": 3.39,
      "cer": 1.18,
      "wer_absolute": 3.39,
      "cer_absolute": 1.18,
      "transcription_length": 2752,
      "is_baseline": false
    },
    {
      "speed": 1.9,
      "wer": 2.97,
      "cer": 1.36,
      "wer_absolute": 2.97,
      "cer_absolute": 1.36,
      "transcription_length": 2747,
      "is_baseline": false
    }
  ],
  "aircAruvnKk": [
    {
      "speed": 1.0,
      "wer": 0.0,
      "cer": 0.0,
      "wer_absolute": 0.0,
      "cer_absolute": 0.0,
      "transcription_length": 18397,
      "is_baseline": true
    },
    {
      "speed": 1.5,
      "wer": 1.14,
      "cer": 0.85,
      "wer_absolute": 1.14,
      "cer_absolute": 0.85,
      "transcription_length": 18467,
      "is_baseline": false
    },
    {
      "speed": 2.0,
      "wer": 1.29,
      "cer": 0.76,
      "wer_absolute": 1.29,
      "cer_absolute": 0.76,
      "transcription_length": 18446,
      "is_baseline": false
    },
    {
      "speed": 2.1,
      "wer": 1.96,
      "cer": 1.33,
      "wer_absolute": 1.96,
      "cer_absolute": 1.33,
      "transcription_length": 18443,
      "is_baseline": false
    },
    {
      "speed": 2.2,
      "wer": 1.91,
      "cer": 1.25,
      "wer_absolute": 1.91,
      "cer_absolute": 1.25,
      "transcription_length": 18461,
      "is_baseline": false
    },
    {
      "speed": 2.5,
      "wer": 3.9,
      "cer": 2.72,
      "wer_absolute": 3.9,
      "cer_absolute": 2.72,
      "transcription_length": 18462,
      "is_baseline": false
    },
    {
      "speed": 1.1,
      "wer": 0.97,
      "cer": 0.71,
      "wer_absolute": 0.97,
      "cer_absolute": 0.71,
      "transcription_length": 18483,
      "is_baseline": false
    },
    {
      "speed": 1.2,
      "wer": 0.85,
      "cer": 0.63,
      "wer_absolute": 0.85,
      "cer_absolute": 0.63,
      "transcription_length": 18497,
      "is_baseline": false
    },
    {
      "speed": 1.3,
      "wer": 1.5,
      "cer": 1.06,
      "wer_absolute": 1.5,
      "cer_absolute": 1.06,
      "transcription_length": 18494,
      "is_baseline": false
    },
    {
      "speed": 1.4,
      "wer": 1.32,
      "cer": 1.04,
      "wer_absolute": 1.32,
      "cer_absolute": 1.04,
      "transcription_length": 18509,
      "is_baseline": false
    },
    {
      "speed": 1.6,
      "wer": 1.29,
      "cer": 0.96,
      "wer_absolute": 1.29,
      "cer_absolute": 0.96,
      "transcription_length": 18524,
      "is_baseline": false
    },
    {
      "speed": 1.7,
      "wer": 1.64,
      "cer": 1.15,
      "wer_absolute": 1.64,
      "cer_absolute": 1.15,
      "transcription_length": 18506,
      "is_baseline": false
    },
    {
      "speed": 1.8,
      "wer": 2.2,
      "cer": 1.59,
      "wer_absolute": 2.2,
      "cer_absolute": 1.59,
      "transcription_length": 18401,
      "is_baseline": false
    },
    {
      "speed": 1.9,
      "wer": 2.26,
      "cer": 1.56,
      "wer_absolute": 2.26,
      "cer_absolute": 1.56,
      "transcription_length": 18404,
      "is_baseline": false
    }
  ],
  "3MqYE2UuN24": [
    {
      "speed": 1.0,
      "wer": 0.0,
      "cer": 0.0,
      "wer_absolute": 0.0,
      "cer_absolute": 0.0,
      "transcription_length": 2265,
      "is_baseline": true
    },
    {
      "speed": 1.5,
      "wer": 0.67,
      "cer": 0.36,
      "wer_absolute": 0.67,
      "cer_absolute": 0.36,
      "transcription_length": 2263,
      "is_baseline": false
    },
    {
      "speed": 1.6,
      "wer": 0.67,
      "cer": 0.41,
      "wer_absolute": 0.67,
      "cer_absolute": 0.41,
      "transcription_length": 2255,
      "is_baseline": false
    },
    {
      "speed": 1.7,
      "wer": 1.79,
      "cer": 0.86,
      "wer_absolute": 1.79,
      "cer_absolute": 0.86,
      "transcription_length": 2261,
      "is_baseline": false
    },
    {
      "speed": 1.8,
      "wer": 1.34,
      "cer": 0.54,
      "wer_absolute": 1.34,
      "cer_absolute": 0.54,
      "transcription_length": 2266,
      "is_baseline": false
    },
    {
      "speed": 2.0,
      "wer": 2.68,
      "cer": 1.26,
      "wer_absolute": 2.68,
      "cer_absolute": 1.26,
      "transcription_length": 2261,
      "is_baseline": false
    },
    {
      "speed": 2.5,
      "wer": 4.03,
      "cer": 2.26,
      "wer_absolute": 4.03,
      "cer_absolute": 2.26,
      "transcription_length": 2251,
      "is_baseline": false
    },
    {
      "speed": 1.1,
      "wer": 0.45,
      "cer": 0.23,
      "wer_absolute": 0.45,
      "cer_absolute": 0.23,
      "transcription_length": 2269,
      "is_baseline": false
    },
    {
      "speed": 1.2,
      "wer": 2.24,
      "cer": 2.12,
      "wer_absolute": 2.24,
      "cer_absolute": 2.12,
      "transcription_length": 2308,
      "is_baseline": false
    },
    {
      "speed": 1.3,
      "wer": 2.24,
      "cer": 2.12,
      "wer_absolute": 2.24,
      "cer_absolute": 2.12,
      "transcription_length": 2312,
      "is_baseline": false
    },
    {
      "speed": 1.4,
      "wer": 6.04,
      "cer": 5.55,
      "wer_absolute": 6.04,
      "cer_absolute": 5.55,
      "transcription_length": 2147,
      "is_baseline": false
    },
    {
      "speed": 1.9,
      "wer": 1.57,
      "cer": 0.68,
      "wer_absolute": 1.57,
      "cer_absolute": 0.68,
      "transcription_length": 2265,
      "is_baseline": false
    }
  ],
  "yWO-cvGETRQ": [
    {
      "speed": 1.0,
      "wer": 0.0,
      "cer": 0.0,
      "wer_absolute": 0.0,
      "cer_absolute": 0.0,
      "transcription_length": 9336,
      "is_baseline": true
    },
    {
      "speed": 1.1,
      "wer": 0.35,
      "cer": 0.4,
      "wer_absolute": 0.35,
      "cer_absolute": 0.4,
      "transcription_length": 9355,
      "is_baseline": false
    },
    {
      "speed": 1.2,
      "wer": 0.71,
      "cer": 0.82,
      "wer_absolute": 0.71,
      "cer_absolute": 0.82,
      "transcription_length": 9303,
      "is_baseline": false
    },
    {
      "speed": 1.5,
      "wer": 0.82,
      "cer": 0.79,
      "wer_absolute": 0.82,
      "cer_absolute": 0.79,
      "transcription_length": 9291,
      "is_baseline": false
    },
    {
      "speed": 2.0,
      "wer": 1.06,
      "cer": 0.74,
      "wer_absolute": 1.06,
      "cer_absolute": 0.74,
      "transcription_length": 9346,
      "is_baseline": false
    },
    {
      "speed": 2.5,
      "wer": 3.83,
      "cer": 2.77,
      "wer_absolute": 3.83,
      "cer_absolute": 2.77,
      "transcription_length": 9251,
      "is_baseline": false
    },
    {
      "speed": 1.3,
      "wer": 0.59,
      "cer": 0.5,
      "wer_absolute": 0.59,
      "cer_absolute": 0.5,
      "transcription_length": 9351,
      "is_baseline": false
    },
    {
      "speed": 1.4,
      "wer": 0.65,
      "cer": 0.7,
      "wer_absolute": 0.65,
      "cer_absolute": 0.7,
      "transcription_length": 9350,
      "is_baseline": false
    },
    {
      "speed": 1.6,
      "wer": 0.65,
      "cer": 0.33,
      "wer_absolute": 0.65,
      "cer_absolute": 0.33,
      "transcription_length": 9339,
      "is_baseline": false
    },
    {
      "speed": 1.7,
      "wer": 0.88,
      "cer": 0.61,
      "wer_absolute": 0.88,
      "cer_absolute": 0.61,
      "transcription_length": 9357,
      "is_baseline": false
    },
    {
      "speed": 1.8,
      "wer": 2.06,
      "cer": 1.41,
      "wer_absolute": 2.06,
      "cer_absolute": 1.41,
      "transcription_length": 9313,
      "is_baseline": false
    },
    {
      "speed": 1.9,
      "wer": 1.65,
      "cer": 1.04,
      "wer_absolute": 1.65,
      "cer_absolute": 1.04,
      "transcription_length": 9331,
      "is_baseline": false
    }
  ],
  "UyyjU8fzEYU": [
    {
      "speed": 1.0,
      "wer": 0.0,
      "cer": 0.0,
      "wer_absolute": 0.0,
      "cer_absolute": 0.0,
      "transcription_length": 14876,
      "is_baseline": true
    },
    {
      "speed": 1.5,
      "wer": 3.58,
      "cer": 2.99,
      "wer_absolute": 3.58,
      "cer_absolute": 2.99,
      "transcription_length": 14641,
      "is_baseline": false
    },
    {
      "speed": 1.8,
      "wer": 7.29,
      "cer": 6.06,
      "wer_absolute": 7.29,
      "cer_absolute": 6.06,
      "transcription_length": 14139,
      "is_baseline": false
    },
    {
      "speed": 1.9,
      "wer": 7.16,
      "cer": 5.95,
      "wer_absolute": 7.16,
      "cer_absolute": 5.95,
      "transcription_length": 14240,
      "is_baseline": false
    },
    {
      "speed": 2.0,
      "wer": 10.28,
      "cer": 8.28,
      "wer_absolute": 10.28,
      "cer_absolute": 8.28,
      "transcription_length": 14300,
      "is_baseline": false
    },
    {
      "speed": 2.5,
      "wer": 20.53,
      "cer": 18.39,
      "wer_absolute": 20.53,
      "cer_absolute": 18.39,
      "transcription_length": 13297,
      "is_baseline": false
    },
    {
      "speed": 1.1,
      "wer": 4.1,
      "cer": 3.5,
      "wer_absolute": 4.1,
      "cer_absolute": 3.5,
      "transcription_length": 14439,
      "is_baseline": false
    },
    {
      "speed": 1.2,
      "wer": 3.2,
      "cer": 3.11,
      "wer_absolute": 3.2,
      "cer_absolute": 3.11,
      "transcription_length": 14824,
      "is_baseline": false
    },
    {
      "speed": 1.3,
      "wer": 4.45,
      "cer": 3.73,
      "wer_absolute": 4.45,
      "cer_absolute": 3.73,
      "transcription_length": 14449,
      "is_baseline": false
    },
    {
      "speed": 1.4,
      "wer": 2.43,
      "cer": 2.06,
      "wer_absolute": 2.43,
      "cer_absolute": 2.06,
      "transcription_length": 14771,
      "is_baseline": false
    },
    {
      "speed": 1.6,
      "wer": 5.7,
      "cer": 4.45,
      "wer_absolute": 5.7,
      "cer_absolute": 4.45,
      "transcription_length": 14618,
      "is_baseline": false
    },
    {
      "speed": 1.7,
      "wer": 4.83,
      "cer": 3.93,
      "wer_absolute": 4.83,
      "cer_absolute": 3.93,
      "transcription_length": 14465,
      "is_baseline": false
    }
  ],
  "tmNXKqeUtJM": [
    {
      "speed": 1.0,
      "wer": 0.0,
      "cer": 0.0,
      "wer_absolute": 0.0,
      "cer_absolute": 0.0,
      "transcription_length": 3452,
      "is_baseline": true
    },
    {
      "speed": 1.5,
      "wer": 0.16,
      "cer": 0.09,
      "wer_absolute": 0.16,
      "cer_absolute": 0.09,
      "transcription_length": 3462,
      "is_baseline": false
    },
    {
      "speed": 1.8,
      "wer": 0.48,
      "cer": 0.12,
      "wer_absolute": 0.48,
      "cer_absolute": 0.12,
      "transcription_length": 3458,
      "is_baseline": false
    },
    {
      "speed": 1.9,
      "wer": 0.96,
      "cer": 0.38,
      "wer_absolute": 0.96,
      "cer_absolute": 0.38,
      "transcription_length": 3459,
      "is_baseline": false
    },
    {
      "speed": 2.0,
      "wer": 8.83,
      "cer": 7.34,
      "wer_absolute": 8.83,
      "cer_absolute": 7.34,
      "transcription_length": 3236,
      "is_baseline": false
    },
    {
      "speed": 2.5,
      "wer": 4.65,
      "cer": 2.23,
      "wer_absolute": 4.65,
      "cer_absolute": 2.23,
      "transcription_length": 3455,
      "is_baseline": false
    },
    {
      "speed": 1.1,
      "wer": 0.0,
      "cer": 0.0,
      "wer_absolute": 0.0,
      "cer_absolute": 0.0,
      "transcription_length": 3461,
      "is_baseline": false
    },
    {
      "speed": 1.2,
      "wer": 0.0,
      "cer": 0.0,
      "wer_absolute": 0.0,
      "cer_absolute": 0.0,
      "transcription_length": 3457,
      "is_baseline": false
    },
    {
      "speed": 1.3,
      "wer": 0.0,
      "cer": 0.0,
      "wer_absolute": 0.0,
      "cer_absolute": 0.0,
      "transcription_length": 3466,
      "is_baseline": false
    },
    {
      "speed": 1.4,
      "wer": 0.32,
      "cer": 0.03,
      "wer_absolute": 0.32,
      "cer_absolute": 0.03,
      "transcription_length": 3453,
      "is_baseline": false
    },
    {
      "speed": 1.6,
      "wer": 1.12,
      "cer": 0.47,
      "wer_absolute": 1.12,
      "cer_absolute": 0.47,
      "transcription_length": 3463,
      "is_baseline": false
    },
    {
      "speed": 1.7,
      "wer": 0.16,
      "cer": 0.09,
      "wer_absolute": 0.16,
      "cer_absolute": 0.09,
      "transcription_length": 3456,
      "is_baseline": false
    }
  ],
  "WUvTyaaNkzM": [
    {
      "speed": 1.0,
      "wer": 0.0,
      "cer": 0.0,
      "wer_absolute": 0.0,
      "cer_absolute": 0.0,
      "transcription_length": 15864,
      "is_baseline": true
    },
    {
      "speed": 1.5,
      "wer": 1.93,
      "cer": 1.19,
      "wer_absolute": 1.93,
      "cer_absolute": 1.19,
      "transcription_length": 16051,
      "is_baseline": false
    },
    {
      "speed": 2.0,
      "wer": 2.23,
      "cer": 1.37,
      "wer_absolute": 2.23,
      "cer_absolute": 1.37,
      "transcription_length": 16057,
      "is_baseline": false
    },
    {
      "speed": 2.1,
      "wer": 3.46,
      "cer": 2.49,
      "wer_absolute": 3.46,
      "cer_absolute": 2.49,
      "transcription_length": 15861,
      "is_baseline": false
    },
    {
      "speed": 2.2,
      "wer": 3.32,
      "cer": 2.33,
      "wer_absolute": 3.32,
      "cer_absolute": 2.33,
      "transcription_length": 15910,
      "is_baseline": false
    },
    {
      "speed": 2.5,
      "wer": 4.75,
      "cer": 3.76,
      "wer_absolute": 4.75,
      "cer_absolute": 3.76,
      "transcription_length": 15671,
      "is_baseline": false
    },
    {
      "speed": 1.1,
      "wer": 1.93,
      "cer": 1.22,
      "wer_absolute": 1.93,
      "cer_absolute": 1.22,
      "transcription_length": 16055,
      "is_baseline": false
    },
    {
      "speed": 1.2,
      "wer": 2.46,
      "cer": 1.68,
      "wer_absolute": 2.46,
      "cer_absolute": 1.68,
      "transcription_length": 16001,
      "is_baseline": false
    },
    {
      "speed": 1.3,
      "wer": 2.39,
      "cer": 1.56,
      "wer_absolute": 2.39,
      "cer_absolute": 1.56,
      "transcription_length": 16080,
      "is_baseline": false
    },
    {
      "speed": 1.4,
      "wer": 2.19,
      "cer": 1.37,
      "wer_absolute": 2.19,
      "cer_absolute": 1.37,
      "transcription_length": 16059,
      "is_baseline": false
    },
    {
      "speed": 1.6,
      "wer": 2.23,
      "cer": 1.39,
      "wer_absolute": 2.23,
      "cer_absolute": 1.39,
      "transcription_length": 16035,
      "is_baseline": false
    },
    {
      "speed": 1.7,
      "wer": 2.06,
      "cer": 1.25,
      "wer_absolute": 2.06,
      "cer_absolute": 1.25,
      "transcription_length": 16061,
      "is_baseline": false
    },
    {
      "speed": 1.8,
      "wer": 2.63,
      "cer": 1.69,
      "wer_absolute": 2.63,
      "cer_absolute": 1.69,
      "transcription_length": 16024,
      "is_baseline": false
    },
    {
      "speed": 1.9,
      "wer": 2.82,
      "cer": 2.03,
      "wer_absolute": 2.82,
      "cer_absolute": 2.03,
      "transcription_length": 15943,
      "is_baseline": false
    }
  ],
  "kTXTPe3wahc": [
    {
      "speed": 1.0,
      "wer": 0.0,
      "cer": 0.0,
      "wer_absolute": 0.0,
      "cer_absolute": 0.0,
      "transcription_length": 20387,
      "is_baseline": true
    },
    {
      "speed": 1.5,
      "wer": 1.9,
      "cer": 0.97,
      "wer_absolute": 1.9,
      "cer_absolute": 0.97,
      "transcription_length": 20405,
      "is_baseline": false
    },
    {
      "speed": 2.0,
      "wer": 8.39,
      "cer": 7.3,
      "wer_absolute": 8.39,
      "cer_absolute": 7.3,
      "transcription_length": 21002,
      "is_baseline": false
    },
    {
      "speed": 2.5,
      "wer": 5.85,
      "cer": 4.02,
      "wer_absolute": 5.85,
      "cer_absolute": 4.02,
      "transcription_length": 19905,
      "is_baseline": false
    },
    {
      "speed": 1.1,
      "wer": 1.09,
      "cer": 0.48,
      "wer_absolute": 1.09,
      "cer_absolute": 0.48,
      "transcription_length": 20431,
      "is_baseline": false
    },
    {
      "speed": 1.2,
      "wer": 0.95,
      "cer": 0.51,
      "wer_absolute": 0.95,
      "cer_absolute": 0.51,
      "transcription_length": 20439,
      "is_baseline": false
    },
    {
      "speed": 1.3,
      "wer": 0.98,
      "cer": 0.45,
      "wer_absolute": 0.98,
      "cer_absolute": 0.45,
      "transcription_length": 20440,
      "is_baseline": false
    },
    {
      "speed": 1.4,
      "wer": 1.25,
      "cer": 0.62,
      "wer_absolute": 1.25,
      "cer_absolute": 0.62,
      "transcription_length": 20419,
      "is_baseline": false
    },
    {
      "speed": 1.6,
      "wer": 1.9,
      "cer": 1.0,
      "wer_absolute": 1.9,
      "cer_absolute": 1.0,
      "transcription_length": 20394,
      "is_baseline": false
    },
    {
      "speed": 1.7,
      "wer": 1.92,
      "cer": 1.11,
      "wer_absolute": 1.92,
      "cer_absolute": 1.11,
      "transcription_length": 20338,
      "is_baseline": false
    },
    {
      "speed": 1.8,
      "wer": 3.57,
      "cer": 2.51,
      "wer_absolute": 3.57,
      "cer_absolute": 2.51,
      "transcription_length": 20059,
      "is_baseline": false
    },
    {
      "speed": 1.9,
      "wer": 4.35,
      "cer": 3.18,
      "wer_absolute": 4.35,
      "cer_absolute": 3.18,
      "transcription_length": 20002,
      "is_baseline": false
    }
  ],
  "XayNKY944lY": [
    {
      "speed": 1.0,
      "wer": 0.0,
      "cer": 0.0,
      "wer_absolute": 0.0,
      "cer_absolute": 0.0,
      "transcription_length": 2858,
      "is_baseline": true
    },
    {
      "speed": 1.1,
      "wer": 17.85,
      "cer": 16.18,
      "wer_absolute": 17.85,
      "cer_absolute": 16.18,
      "transcription_length": 3313,
      "is_baseline": false
    },
    {
      "speed": 1.2,
      "wer": 17.27,
      "cer": 15.86,
      "wer_absolute": 17.27,
      "cer_absolute": 15.86,
      "transcription_length": 3311,
      "is_baseline": false
    },
    {
      "speed": 1.5,
      "wer": 16.89,
      "cer": 15.18,
      "wer_absolute": 16.89,
      "cer_absolute": 15.18,
      "transcription_length": 3287,
      "is_baseline": false
    },
    {
      "speed": 2.0,
      "wer": 18.04,
      "cer": 16.04,
      "wer_absolute": 18.04,
      "cer_absolute": 16.04,
      "transcription_length": 3310,
      "is_baseline": false
    },
    {
      "speed": 2.5,
      "wer": 19.58,
      "cer": 16.65,
      "wer_absolute": 19.58,
      "cer_absolute": 16.65,
      "transcription_length": 3300,
      "is_baseline": false
    },
    {
      "speed": 1.3,
      "wer": 17.66,
      "cer": 15.97,
      "wer_absolute": 17.66,
      "cer_absolute": 15.97,
      "transcription_length": 3310,
      "is_baseline": false
    },
    {
      "speed": 1.4,
      "wer": 17.66,
      "cer": 15.97,
      "wer_absolute": 17.66,
      "cer_absolute": 15.97,
      "transcription_length": 3311,
      "is_baseline": false
    },
    {
      "speed": 1.6,
      "wer": 17.66,
      "cer": 15.97,
      "wer_absolute": 17.66,
      "cer_absolute": 15.97,
      "transcription_length": 3309,
      "is_baseline": false
    },
    {
      "speed": 1.7,
      "wer": 17.66,
      "cer": 15.97,
      "wer_absolute": 17.66,
      "cer_absolute": 15.97,
      "transcription_length": 3306,
      "is_baseline": false
    },
    {
      "speed": 1.8,
      "wer": 17.85,
      "cer": 16.0,
      "wer_absolute": 17.85,
      "cer_absolute": 16.0,
      "transcription_length": 3308,
      "is_baseline": false
    },
    {
      "speed": 1.9,
      "wer": 18.04,
      "cer": 16.04,
      "wer_absolute": 18.04,
      "cer_absolute": 16.04,
      "transcription_length": 3314,
      "is_baseline": false
    }
  ],
  "engineerguy_microwave": [
    {
      "speed": 1.0,
      "wer": 0.0,
      "cer": 0.0,
      "wer_absolute": 0.0,
      "cer_absolute": 0.0,
      "transcription_length": 4582,
      "is_baseline": true
    },
    {
      "speed": 1.5,
      "wer": 1.26,
      "cer": 0.64,
      "wer_absolute": 1.26,
      "cer_absolute": 0.64,
      "transcription_length": 4610,
      "is_baseline": false
    },
    {
      "speed": 1.6,
      "wer": 1.77,
      "cer": 0.78,
      "wer_absolute": 1.77,
      "cer_absolute": 0.78,
      "transcription_length": 4592,
      "is_baseline": false
    },
    {
      "speed": 1.7,
      "wer": 1.52,
      "cer": 0.78,
      "wer_absolute": 1.52,
      "cer_absolute": 0.78,
      "transcription_length": 4594,
      "is_baseline": false
    },
    {
      "speed": 1.8,
      "wer": 2.02,
      "cer": 1.13,
      "wer_absolute": 2.02,
      "cer_absolute": 1.13,
      "transcription_length": 4608,
      "is_baseline": false
    },
    {
      "speed": 2.0,
      "wer": 13.91,
      "cer": 11.2,
      "wer_absolute": 13.91,
      "cer_absolute": 11.2,
      "transcription_length": 5010,
      "is_baseline": false
    },
    {
      "speed": 2.5,
      "wer": 14.03,
      "cer": 10.25,
      "wer_absolute": 14.03,
      "cer_absolute": 10.25,
      "transcription_length": 4362,
      "is_baseline": false
    },
    {
      "speed": 1.1,
      "wer": 2.15,
      "cer": 1.35,
      "wer_absolute": 2.15,
      "cer_absolute": 1.35,
      "transcription_length": 4580,
      "is_baseline": false
    },
    {
      "speed": 1.2,
      "wer": 1.77,
      "cer": 1.31,
      "wer_absolute": 1.77,
      "cer_absolute": 1.31,
      "transcription_length": 4603,
      "is_baseline": false
    },
    {
      "speed": 1.3,
      "wer": 2.02,
      "cer": 1.26,
      "wer_absolute": 2.02,
      "cer_absolute": 1.26,
      "transcription_length": 4585,
      "is_baseline": false
    },
    {
      "speed": 1.4,
      "wer": 10.37,
      "cer": 8.65,
      "wer_absolute": 10.37,
      "cer_absolute": 8.65,
      "transcription_length": 4963,
      "is_baseline": false
    },
    {
      "speed": 1.9,
      "wer": 2.91,
      "cer": 1.42,
      "wer_absolute": 2.91,
      "cer_absolute": 1.42,
      "transcription_length": 4585,
      "is_baseline": false
    }
  ],
  "kurzgesagt_quantum": [
    {
      "speed": 1.0,
      "wer": 0.0,
      "cer": 0.0,
      "wer_absolute": 0.0,
      "cer_absolute": 0.0,
      "transcription_length": 6993,
      "is_baseline": true
    },
    {
      "speed": 1.5,
      "wer": 0.08,
      "cer": 0.07,
      "wer_absolute": 0.08,
      "cer_absolute": 0.07,
      "transcription_length": 6991,
      "is_baseline": false
    },
    {
      "speed": 1.6,
      "wer": 0.41,
      "cer": 0.36,
      "wer_absolute": 0.41,
      "cer_absolute": 0.36,
      "transcription_length": 6978,
      "is_baseline": false
    },
    {
      "speed": 1.7,
      "wer": 0.08,
      "cer": 0.07,
      "wer_absolute": 0.08,
      "cer_absolute": 0.07,
      "transcription_length": 6991,
      "is_baseline": false
    },
    {
      "speed": 1.8,
      "wer": 0.5,
      "cer": 0.39,
      "wer_absolute": 0.5,
      "cer_absolute": 0.39,
      "transcription_length": 7005,
      "is_baseline": false
    },
    {
      "speed": 1.9,
      "wer": 0.5,
      "cer": 0.29,
      "wer_absolute": 0.5,
      "cer_absolute": 0.29,
      "transcription_length": 6996,
      "is_baseline": false
    },
    {
      "speed": 2.0,
      "wer": 1.74,
      "cer": 1.38,
      "wer_absolute": 1.74,
      "cer_absolute": 1.38,
      "transcription_length": 6909,
      "is_baseline": false
    },
    {
      "speed": 2.5,
      "wer": 1.91,
      "cer": 1.19,
      "wer_absolute": 1.91,
      "cer_absolute": 1.19,
      "transcription_length": 6968,
      "is_baseline": false
    },
    {
      "speed": 1.1,
      "wer": 0.5,
      "cer": 0.39,
      "wer_absolute": 0.5,
      "cer_absolute": 0.39,
      "transcription_length": 6980,
      "is_baseline": false
    },
    {
      "speed": 1.2,
      "wer": 0.17,
      "cer": 0.12,
      "wer_absolute": 0.17,
      "cer_absolute": 0.12,
      "transcription_length": 6989,
      "is_baseline": false
    },
    {
      "speed": 1.3,
      "wer": 1.08,
      "cer": 0.84,
      "wer_absolute": 1.08,
      "cer_absolute": 0.84,
      "transcription_length": 6995,
      "is_baseline": false
    },
    {
      "speed": 1.4,
      "wer": 0.08,
      "cer": 0.07,
      "wer_absolute": 0.08,
      "cer_absolute": 0.07,
      "transcription_length": 6989,
      "is_baseline": false
    }
  ],
  "Ywn2Lz5zmYg": [
    {
      "speed": 1.0,
      "wer": 0.0,
      "cer": 0.0,
      "wer_absolute": 0.0,
      "cer_absolute": 0.0,
      "transcription_length": 5364,
      "is_baseline": true
    },
    {
      "speed": 1.2,
      "wer": 0.11,
      "cer": 0.02,
      "wer_absolute": 0.11,
      "cer_absolute": 0.02,
      "transcription_length": 5367,
      "is_baseline": false
    },
    {
      "speed": 1.3,
      "wer": 0.22,
      "cer": 0.08,
      "wer_absolute": 0.22,
      "cer_absolute": 0.08,
      "transcription_length": 5362,
      "is_baseline": false
    },
    {
      "speed": 1.4,
      "wer": 0.32,
      "cer": 0.34,
      "wer_absolute": 0.32,
      "cer_absolute": 0.34,
      "transcription_length": 5377,
      "is_baseline": false
    },
    {
      "speed": 1.5,
      "wer": 0.54,
      "cer": 0.32,
      "wer_absolute": 0.54,
      "cer_absolute": 0.32,
      "transcription_length": 5355,
      "is_baseline": false
    },
    {
      "speed": 1.6,
      "wer": 1.51,
      "cer": 1.31,
      "wer_absolute": 1.51,
      "cer_absolute": 1.31,
      "transcription_length": 5318,
      "is_baseline": false
    },
    {
      "speed": 1.8,
      "wer": 0.65,
      "cer": 0.59,
      "wer_absolute": 0.65,
      "cer_absolute": 0.59,
      "transcription_length": 5405,
      "is_baseline": false
    },
    {
      "speed": 2.0,
      "wer": 1.29,
      "cer": 0.78,
      "wer_absolute": 1.29,
      "cer_absolute": 0.78,
      "transcription_length": 5396,
      "is_baseline": false
    },
    {
      "speed": 2.5,
      "wer": 12.26,
      "cer": 10.92,
      "wer_absolute": 12.26,
      "cer_absolute": 10.92,
      "transcription_length": 4825,
      "is_baseline": false
    },
    {
      "speed": 1.1,
      "wer": 0.86,
      "cer": 0.66,
      "wer_absolute": 0.86,
      "cer_absolute": 0.66,
      "transcription_length": 5340,
      "is_baseline": false
    },
    {
      "speed": 1.7,
      "wer": 0.75,
      "cer": 0.76,
      "wer_absolute": 0.75,
      "cer_absolute": 0.76,
      "transcription_length": 5397,
      "is_baseline": false
    },
    {
      "speed": 1.9,
      "wer": 1.72,
      "cer": 1.31,
      "wer_absolute": 1.72,
      "cer_absolute": 1.31,
      "transcription_length": 5397,
      "is_baseline": false
    }
  ],
  "2UHS883_P60": [
    {
      "speed": 1.0,
      "wer": 0.0,
      "cer": 0.0,
      "wer_absolute": 0.0,
      "cer_absolute": 0.0,
      "transcription_length": 3532,
      "is_baseline": true
    },
    {
      "speed": 1.5,
      "wer": 1.38,
      "cer": 0.98,
      "wer_absolute": 1.38,
      "cer_absolute": 0.98,
      "transcription_length": 3502,
      "is_baseline": false
    },
    {
      "speed": 1.8,
      "wer": 3.53,
      "cer": 2.73,
      "wer_absolute": 3.53,
      "cer_absolute": 2.73,
      "transcription_length": 3469,
      "is_baseline": false
    },
    {
      "speed": 1.9,
      "wer": 2.61,
      "cer": 1.96,
      "wer_absolute": 2.61,
      "cer_absolute": 1.96,
      "transcription_length": 3507,
      "is_baseline": false
    },
    {
      "speed": 2.0,
      "wer": 45.25,
      "cer": 45.37,
      "wer_absolute": 45.25,
      "cer_absolute": 45.37,
      "transcription_length": 5057,
      "is_baseline": false
    },
    {
      "speed": 2.5,
      "wer": 2.45,
      "cer": 1.09,
      "wer_absolute": 2.45,
      "cer_absolute": 1.09,
      "transcription_length": 3506,
      "is_baseline": false
    },
    {
      "speed": 1.1,
      "wer": 0.61,
      "cer": 0.35,
      "wer_absolute": 0.61,
      "cer_absolute": 0.35,
      "transcription_length": 3532,
      "is_baseline": false
    },
    {
      "speed": 1.2,
      "wer": 2.61,
      "cer": 1.61,
      "wer_absolute": 2.61,
      "cer_absolute": 1.61,
      "transcription_length": 3497,
      "is_baseline": false
    },
    {
      "speed": 1.3,
      "wer": 0.61,
      "cer": 0.35,
      "wer_absolute": 0.61,
      "cer_absolute": 0.35,
      "transcription_length": 3535,
      "is_baseline": false
    },
    {
      "speed": 1.4,
      "wer": 0.92,
      "cer": 0.52,
      "wer_absolute": 0.92,
      "cer_absolute": 0.52,
      "transcription_length": 3532,
      "is_baseline": false
    },
    {
      "speed": 1.6,
      "wer": 1.84,
      "cer": 1.29,
      "wer_absolute": 1.84,
      "cer_absolute": 1.29,
      "transcription_length": 3496,
      "is_baseline": false
    },
    {
      "speed": 1.7,
      "wer": 3.99,
      "cer": 3.19,
      "wer_absolute": 3.99,
      "cer_absolute": 3.19,
      "transcription_length": 3477,
      "is_baseline": false
    }
  ],
  "3PszVWZNWVA": [
    {
      "speed": 1.0,
      "wer": 0.0,
      "cer": 0.0,
      "wer_absolute": 0.0,
      "cer_absolute": 0.0,
      "transcription_length": 14593,
      "is_baseline": true
    },
    {
      "speed": 1.5,
      "wer": 1.26,
      "cer": 0.84,
      "wer_absolute": 1.26,
      "cer_absolute": 0.84,
      "transcription_length": 14592,
      "is_baseline": false
    },
    {
      "speed": 1.6,
      "wer": 3.78,
      "cer": 2.93,
      "wer_absolute": 3.78,
      "cer_absolute": 2.93,
      "transcription_length": 14255,
      "is_baseline": false
    },
    {
      "speed": 1.8,
      "wer": 1.49,
      "cer": 0.81,
      "wer_absolute": 1.49,
      "cer_absolute": 0.81,
      "transcription_length": 14544,
      "is_baseline": false
    },
    {
      "speed": 1.9,
      "wer": 5.23,
      "cer": 4.22,
      "wer_absolute": 5.23,
      "cer_absolute": 4.22,
      "transcription_length": 14189,
      "is_baseline": false
    },
    {
      "speed": 2.0,
      "wer": 4.58,
      "cer": 3.67,
      "wer_absolute": 4.58,
      "cer_absolute": 3.67,
      "transcription_length": 14206,
      "is_baseline": false
    },
    {
      "speed": 2.5,
      "wer": 5.69,
      "cer": 3.27,
      "wer_absolute": 5.69,
      "cer_absolute": 3.27,
      "transcription_length": 14428,
      "is_baseline": false
    },
    {
      "speed": 1.1,
      "wer": 0.76,
      "cer": 0.42,
      "wer_absolute": 0.76,
      "cer_absolute": 0.42,
      "transcription_length": 14578,
      "is_baseline": false
    },
    {
      "speed": 1.2,
      "wer": 1.68,
      "cer": 0.94,
      "wer_absolute": 1.68,
      "cer_absolute": 0.94,
      "transcription_length": 14635,
      "is_baseline": false
    },
    {
      "speed": 1.3,
      "wer": 1.37,
      "cer": 0.77,
      "wer_absolute": 1.37,
      "cer_absolute": 0.77,
      "transcription_length": 14654,
      "is_baseline": false
    },
    {
      "speed": 1.4,
      "wer": 1.72,
      "cer": 1.18,
      "wer_absolute": 1.72,
      "cer_absolute": 1.18,
      "transcription_length": 14577,
      "is_baseline": false
    },
    {
      "speed": 1.7,
      "wer": 3.13,
      "cer": 2.59,
      "wer_absolute": 3.13,
      "cer_absolute": 2.59,
      "transcription_length": 14283,
      "is_baseline": false
    }
  ],
  "IJhgZBn-LHg": [
    {
      "speed": 1.0,
      "wer": 0.0,
      "cer": 0.0,
      "wer_absolute": 0.0,
      "cer_absolute": 0.0,
      "transcription_length": 16258,
      "is_baseline": true
    },
    {
      "speed": 1.5,
      "wer": 4.89,
      "cer": 4.62,
      "wer_absolute": 4.89,
      "cer_absolute": 4.62,
      "transcription_length": 15636,
      "is_baseline": false
    },
    {
      "speed": 2.0,
      "wer": 2.23,
      "cer": 1.27,
      "wer_absolute": 2.23,
      "cer_absolute": 1.27,
      "transcription_length": 16243,
      "is_baseline": false
    },
    {
      "speed": 2.5,
      "wer": 4.06,
      "cer": 2.69,
      "wer_absolute": 4.06,
      "cer_absolute": 2.69,
      "transcription_length": 16004,
      "is_baseline": false
    },
    {
      "speed": 1.1,
      "wer": 1.4,
      "cer": 0.71,
      "wer_absolute": 1.4,
      "cer_absolute": 0.71,
      "transcription_length": 16297,
      "is_baseline": false
    },
    {
      "speed": 1.2,
      "wer": 1.26,
      "cer": 0.79,
      "wer_absolute": 1.26,
      "cer_absolute": 0.79,
      "transcription_length": 16234,
      "is_baseline": false
    },
    {
      "speed": 1.3,
      "wer": 0.9,
      "cer": 0.37,
      "wer_absolute": 0.9,
      "cer_absolute": 0.37,
      "transcription_length": 16238,
      "is_baseline": false
    },
    {
      "speed": 1.4,
      "wer": 1.4,
      "cer": 0.78,
      "wer_absolute": 1.4,
      "cer_absolute": 0.78,
      "transcription_length": 16250,
      "is_baseline": false
    },
    {
      "speed": 1.6,
      "wer": 1.36,
      "cer": 0.83,
      "wer_absolute": 1.36,
      "cer_absolute": 0.83,
      "transcription_length": 16267,
      "is_baseline": false
    },
    {
      "speed": 1.7,
      "wer": 1.36,
      "cer": 0.88,
      "wer_absolute": 1.36,
      "cer_absolute": 0.88,
      "transcription_length": 16255,
      "is_baseline": false
    },
    {
      "speed": 1.8,
      "wer": 1.56,
      "cer": 0.92,
      "wer_absolute": 1.56,
      "cer_absolute": 0.92,
      "transcription_length": 16260,
      "is_baseline": false
    },
    {
      "speed": 1.9,
      "wer": 1.93,
      "cer": 1.17,
      "wer_absolute": 1.93,
      "cer_absolute": 1.17,
      "transcription_length": 16259,
      "is_baseline": false
    }
  ]
}